[
  {
    "ppt_type": "Training",
    "ppt_label": "1",
    "paper_category": "Training",
    "paper_label": "Color",
    "correct": 4,
    "paper_number": 1
  },
  {
    "ppt_type": "Training",
    "ppt_label": "2",
    "paper_category": "Training",
    "paper_label": "Orientation",
    "correct": 3,
    "paper_number": 2

  },
  {
    "ppt_type": "Topology",
    "ppt_label": "Holes",
    "paper_category": "Topology",
    "paper_label": "Holes",
    "correct": 4,
    "paper_number": 6

  },
  {
    "ppt_type": "Topology",
    "ppt_label": "Inside/Outside",
    "paper_category": "Topology",
    "paper_label": "Inside",
    "correct": 1,
    "paper_number": 3

  },
  {
    "ppt_type": "Topology",
    "ppt_label": "Closure",
    "paper_category": "Topology",
    "paper_label": "Closure",
    "correct": 2,
    "paper_number": 4

  },
  {
    "ppt_type": "Topology",
    "ppt_label": "Connexity",
    "paper_category": "Topology",
    "paper_label": "Connectedness",
    "correct": 5,
    "paper_number": 5

  },
  {
    "ppt_type": "Topology",
    "ppt_label": "Belongs to",
    "paper_category": "Euclidean geometry",
    "paper_label": "Alignment of points in lines",
    "correct": 4,
    "paper_number": 9

  },
  {
    "ppt_type": "Geometry",
    "ppt_label": "Line 1",
    "paper_category": "Euclidean geometry",
    "paper_label": "Curve",
    "correct": 5,
    "paper_number": 8

  },
  {
    "ppt_type": "Geometry",
    "ppt_label": "Convexity",
    "paper_category": "Geometrical figures",
    "paper_label": "Convex shape",
    "correct": 5,
    "paper_number": 23

  },
  {
    "ppt_type": "Geometry",
    "ppt_label": "Line 2",
    "paper_category": "Euclidean geometry",
    "paper_label": "Straight line",
    "correct": 2,
    "paper_number": 7
  },
  {
    "ppt_type": "Geometry",
    "ppt_label": "Line 3",
    "paper_category": "Euclidean geometry",
    "paper_label": "Alignment of points in lines",
    "correct": 1,
    "paper_number": 10
  },
  {
    "ppt_type": "Geometry",
    "ppt_label": "Quadrilateral",
    "paper_category": "Geometrical figures",
    "paper_label": "Quadilateral",
    "correct": 1,
    "paper_number": 15
  },
  {
    "ppt_type": "Geometry",
    "ppt_label": "Right Angle 1",
    "paper_category": "Geometrical figures",
    "paper_label": "Right angled triangle",
    "correct": 5,
    "paper_number": 21
  },
  {
    "ppt_type": "Geometry",
    "ppt_label": "Right Angle 2",
    "paper_category": "Euclidean geometry",
    "paper_label": "Right angle",
    "correct": 6,
    "paper_number": 13
  },
  {
    "ppt_type": "Geometry",
    "ppt_label": "Right Angle 3",
    "paper_category": "Euclidean geometry",
    "paper_label": "Right angle",
    "correct": 5,
    "paper_number": 14
  },
  {
    "ppt_type": "Geometry",
    "ppt_label": "Distance",
    "paper_category": "Metric properties",
    "paper_label": "Distance",
    "correct": 6,
    "paper_number": 31
  },
  {
    "ppt_type": "Geometry",
    "ppt_label": "Circle 1",
    "paper_category": "Geometrical figures",
    "paper_label": "Circle",
    "correct": 2,
    "paper_number": 22
  },
  {
    "ppt_type": "Geometry",
    "ppt_label": "Circle 2",
    "paper_category": "Metric properties",
    "paper_label": "Center of circle",
    "correct": 1,
    "paper_number": 34
  },
  {
    "ppt_type": "Geometry",
    "ppt_label": "Midpoint",
    "paper_category": "Metric properties",
    "paper_label": "Middle of segment",
    "correct": 1,
    "paper_number": 36
  },
  {
    "ppt_type": "Geometry",
    "ppt_label": "Equilateral triangle",
    "paper_category": "Geometrical figures",
    "paper_label": "Equilateral triangle",
    "correct": 3,
    "paper_number": 20
  },
  {
    "ppt_type": "Geometry",
    "ppt_label": "Proportion 1:3",
    "paper_category": "Metric properties",
    "paper_label": "Fixed proportion",
    "correct": 4,
    "paper_number": 37
  },
  {
    "ppt_type": "Geometry",
    "ppt_label": "Diagonals",
    "paper_category": "Metric properties",
    "paper_label": "Center of quadilateral",
    "correct": 5,
    "paper_number": 35
  },
  {
    "ppt_type": "Geometry",
    "ppt_label": "Square",
    "paper_category": "Geometrical figures",
    "paper_label": "Square",
    "correct": 4,
    "paper_number": 19
  },
  {
    "ppt_type": "Geometry",
    "ppt_label": "Rectangle",
    "paper_category": "Geometrical figures",
    "paper_label": "Rectangle",
    "correct": 3,
    "paper_number": 18
  },
  {
    "ppt_type": "Geometry",
    "ppt_label": "Parallelogram",
    "paper_category": "Geometrical figures",
    "paper_label": "Parallelogram",
    "correct": 2,
    "paper_number": 17
  },
  {
    "ppt_type": "Geometry",
    "ppt_label": "Trapezoid",
    "paper_category": "Geometrical figures",
    "paper_label": "Trapezoid",
    "correct": 3,
    "paper_number": 16
  },
  {
    "ppt_type": "Transformation",
    "ppt_label": "Axial Symmetry (vertical)",
    "paper_category": "Geometrical transformations",
    "paper_label": "Vertical symmetry",
    "correct": 4,
    "paper_number": 42
  },
  {
    "ppt_type": "Geometry",
    "ppt_label": "Axial Symmetry (vertical)",
    "paper_category": "Symmetrical figures",
    "paper_label": "Vertical axis",
    "correct": 3,
    "paper_number": 24
  },
  {
    "ppt_type": "Geometry",
    "ppt_label": "Axial Symmetry (horizontal)",
    "paper_category": "Symmetrical figures",
    "paper_label": "Horizontal axis",
    "correct": 6,
    "paper_number": 25
  },
  {
    "ppt_type": "Geometry",
    "ppt_label": "Axial Symmetry (random axis)",
    "paper_category": "Symmetrical figures",
    "paper_label": "Oblique axis",
    "correct": 5,
    "paper_number": 26
  },
  {
    "ppt_type": "Transformation",
    "ppt_label": "Translation",
    "paper_category": "Geometrical transformations",
    "paper_label": "Translation",
    "correct": 2,
    "paper_number": 38
  },
  {
    "ppt_type": "Transformation",
    "ppt_label": "Point symmetry",
    "paper_category": "Geometrical transformations",
    "paper_label": "Point symmetry",
    "correct": 6,
    "paper_number": 44
  },
  {
    "ppt_type": "Transformation",
    "ppt_label": "Axial Symmetry (horizontal)",
    "paper_category": "Geometrical transformations",
    "paper_label": "Horizontal symmetry",
    "correct": 2,
    "paper_number": 41
  },
  {
    "ppt_type": "Transformation",
    "ppt_label": "Rotation",
    "paper_category": "Geometrical transformations",
    "paper_label": "Rotation",
    "correct": 6,
    "paper_number": 45
  },
  {
    "ppt_type": "Transformation",
    "ppt_label": "Axial Symmetry (mixed)",
    "paper_category": "Geometrical transformations",
    "paper_label": "Oblique symmetry",
    "correct": 1,
    "paper_number": 43
  },
  {
    "ppt_type": "Transformation",
    "ppt_label": "Homothety",
    "paper_category": "Geometrical transformations",
    "paper_label": "Homothecy (fixed orientation)",
    "correct": 6,
    "paper_number": 39
  },
  {
    "ppt_type": "Geometry",
    "ppt_label": "Parallels 1",
    "paper_category": "Euclidean geometry",
    "paper_label": "Parallel lines",
    "correct": 3,
    "paper_number": 11
  },
  {
    "ppt_type": "Geometry",
    "ppt_label": "Chirality 1",
    "paper_category": "Chiral figures",
    "paper_label": "Oblique axis",
    "correct": 6,
    "paper_number": 29
  },
  {
    "ppt_type": "Geometry",
    "ppt_label": "Proportions",
    "paper_category": "Geometrical transformations",
    "paper_label": "Homothecy (fixed size)",
    "correct": 1,
    "paper_number": 40
  },
  {
    "ppt_type": "Geometry",
    "ppt_label": "Parallels 2",
    "paper_category": "Euclidean geometry",
    "paper_label": "Secant lines",
    "correct": 5,
    "paper_number": 12
  },
  {
    "ppt_type": "Geometry",
    "ppt_label": "Chirality 2",
    "paper_category": "Chiral figures",
    "paper_label": "Vertical axis",
    "correct": 2,
    "paper_number": 27
  },
  {
    "ppt_type": "Geometry",
    "ppt_label": "Chirality 3",
    "paper_category": "Chiral figures",
    "paper_label": "Vertical axis",
    "correct": 3,
    "paper_number": 28
  },
  {
    "ppt_type": "Series",
    "ppt_label": "Arithmetic",
    "paper_category": "Metric properties",
    "paper_label": "Equidistance",
    "correct": 6,
    "paper_number": 32
  },
  {
    "ppt_type": "Geometry",
    "ppt_label": "Chirality 4",
    "paper_category": "Chiral figures",
    "paper_label": "Oblique axis",
    "correct": 4,
    "paper_number": 30
  },
  {
    "ppt_type": "Series",
    "ppt_label": "Geometric",
    "paper_category": "Metric properties",
    "paper_label": "Increasing distance",
    "correct": 3,
    "paper_number": 33
  }
]
